stackit/scf/__init__.py
stackit/scf/api/__init__.py
stackit/scf/api/default_api.py
stackit/scf/api_client.py
stackit/scf/api_response.py
stackit/scf/configuration.py
stackit/scf/exceptions.py
stackit/scf/models/__init__.py
stackit/scf/models/apply_organization_quota_payload.py
stackit/scf/models/create_org_role_payload.py
stackit/scf/models/create_organization_payload.py
stackit/scf/models/create_space_payload.py
stackit/scf/models/create_space_role_payload.py
stackit/scf/models/error_response.py
stackit/scf/models/isolation_segment.py
stackit/scf/models/isolation_segments_list.py
stackit/scf/models/org_manager.py
stackit/scf/models/org_manager_delete_response.py
stackit/scf/models/org_manager_response.py
stackit/scf/models/org_role_create_bff_request.py
stackit/scf/models/org_role_response.py
stackit/scf/models/org_role_type.py
stackit/scf/models/organization.py
stackit/scf/models/organization_create_bff_response.py
stackit/scf/models/organization_create_response.py
stackit/scf/models/organization_delete_response.py
stackit/scf/models/organization_quota.py
stackit/scf/models/organization_usage_summary.py
stackit/scf/models/organizations_list.py
stackit/scf/models/organizations_list_item.py
stackit/scf/models/pagination.py
stackit/scf/models/platform_list.py
stackit/scf/models/platforms.py
stackit/scf/models/quota.py
stackit/scf/models/quota_apps.py
stackit/scf/models/quota_domains.py
stackit/scf/models/quota_routes.py
stackit/scf/models/quota_services.py
stackit/scf/models/space.py
stackit/scf/models/space_created_bff_response.py
stackit/scf/models/space_delete_response.py
stackit/scf/models/space_role_create_bff_request.py
stackit/scf/models/space_role_create_bff_response.py
stackit/scf/models/space_role_create_response.py
stackit/scf/models/space_role_type.py
stackit/scf/models/space_with_isolation_segment.py
stackit/scf/models/spaces_list.py
stackit/scf/models/update_organization_payload.py
stackit/scf/models/update_space_payload.py
stackit_scf-0.4.0.dist-info/METADATA
stackit_scf-0.4.0.dist-info/WHEEL
stackit_scf-0.4.0.dist-info/licenses/LICENSE.md
stackit_scf-0.4.0.dist-info/licenses/NOTICE.txt
stackit_scf-0.4.0.dist-info/RECORD
